CHANGES.txt
README.txt
buildout.cfg
setup.py
src/zc/__init__.py
src/zc.extrinsicreference.egg-info/PKG-INFO
src/zc.extrinsicreference.egg-info/SOURCES.txt
src/zc.extrinsicreference.egg-info/dependency_links.txt
src/zc.extrinsicreference.egg-info/namespace_packages.txt
src/zc.extrinsicreference.egg-info/not-zip-safe
src/zc.extrinsicreference.egg-info/requires.txt
src/zc.extrinsicreference.egg-info/top_level.txt
src/zc/extrinsicreference/README.txt
src/zc/extrinsicreference/__init__.py
src/zc/extrinsicreference/configure.zcml
src/zc/extrinsicreference/interfaces.py
src/zc/extrinsicreference/tests.py
src/zc/extrinsicreference/track_shortcuts.zcml